[{"_id":5903299,"formulaStrippedArticleTitle":"Design of eight-band oversampled linear phase paraunitary filter banks using quaternion multiplication matrices","nonIeeeCitationCount":"0","contentTypeDisplay":"Conferences","patentCitationCount":"0","mlTime":"PT0.006933S","lastupdate":"2021-07-23","title":"Design of eight-band oversampled linear phase paraunitary filter banks using quaternion multiplication matrices","contentType":"conferences","ieeeCitationCount":"0","publicationNumber":"5871958"},{"_id":5903301,"formulaStrippedArticleTitle":"LDPC code optimization for diversity reception and turbo equalization","paperCitations":{"ieee":[{"order":"1","displayText":"Christian Cabirol, Wolfgang Sauer-Greff, Andreas Bisplinghoff, Ralph Urbansky, \"Complexity reduced turbo differential decoding based on layered LDPC decoding\", <i>Signal Processing: Algorithms Architectures Arrangements and Applications (SPA) 2015</i>, pp. 119-123, 2015.","links":{"documentLink":"/document/7365145","pdfLink":"/stamp/stamp.jsp?tp=&arnumber=7365145","pdfSize":"804KB"},"title":"Complexity reduced turbo differential decoding based on layered LDPC decoding"}]},"nonIeeeCitationCount":"0","contentTypeDisplay":"Conferences","patentCitationCount":"1","mlTime":"PT0.074292S","lastupdate":"2021-09-10","title":"LDPC code optimization for diversity reception and turbo equalization","contentType":"conferences","ieeeCitationCount":"1","publicationNumber":"5871958"},{"_id":5903302,"paperCitations":{"nonIeee":[{"order":"1","displayText":"Serkan Aras, Manel Hamdi, \"Data Size Requirement for Forecasting Daily Crude Oil Price with Neural Networks\", <i>Scientific Annals of Economics and Business</i>, vol. 66, pp. 363, 2019.","links":{"crossRefLink":"https://doi.org/10.47743/saeb-2019-0027"},"title":"Data Size Requirement for Forecasting Daily Crude Oil Price with Neural Networks"}]},"formulaStrippedArticleTitle":"Optimization of hidden layer in a neural network used to predict bladder-cancer patient-survival","nonIeeeCitationCount":"1","contentTypeDisplay":"Conferences","patentCitationCount":"0","mlTime":"PT0.016369S","lastupdate":"2021-11-13","title":"Optimization of hidden layer in a neural network used to predict bladder-cancer patient-survival","contentType":"conferences","ieeeCitationCount":"0","publicationNumber":"5871958"},{"_id":5903304,"formulaStrippedArticleTitle":"Timing errors analysis of OFDM systems based on joint Cyclic-prefix and postfix","nonIeeeCitationCount":"0","contentTypeDisplay":"Conferences","patentCitationCount":"0","mlTime":"PT0.011652S","lastupdate":"2021-07-23","title":"Timing errors analysis of OFDM systems based on joint Cyclic-prefix and postfix","contentType":"conferences","ieeeCitationCount":"0","publicationNumber":"5871958"}]